README.rst
setup.py
SCImputer/__init__.py
SCImputer.egg-info/PKG-INFO
SCImputer.egg-info/SOURCES.txt
SCImputer.egg-info/dependency_links.txt
SCImputer.egg-info/entry_points.txt
SCImputer.egg-info/not-zip-safe
SCImputer.egg-info/top_level.txt