Metadata-Version: 1.0
Name: SCImputer
Version: 0.0.1
Summary: 利用11种插补算法来填补单细胞测序数据缺失值
Home-page: https://github.com/histmeisah/SC-sequencing-imputer
Author: 马纬彧
Author-email: 740988193@qq.com
License: GPL=3.0
Keywords: imputation
Platform: UNKNOWN
